[
  {
    "canonical_biomarker": "K‑SADS‑MRS",
    "total_count": "145 / 283",
    "total_percentage": "51.24 %",
    "variant_percentages": {
      "K‑SADS‑MRS": "100.00 %"
    },
    "rows": {
      "K‑SADS‑MRS": [
        3,
        4,
        5,
        6,
        7,
        8,
        9,
        10,
        12,
        17,
        20,
        21,
        22,
        23,
        24,
        25,
        27,
        29,
        32,
        39,
        40,
        41,
        42,
        43,
        44,
        47,
        51,
        57,
        61,
        62,
        63,
        64,
        66,
        68,
        73,
        76,
        77,
        78,
        79,
        82,
        85,
        86,
        87,
        91,
        92,
        93,
        94,
        95,
        96,
        98,
        99,
        100,
        103,
        107,
        108,
        112,
        114,
        115,
        117,
        120,
        123,
        124,
        125,
        127,
        131,
        132,
        133,
        137,
        139,
        140,
        142,
        143,
        149,
        150,
        151,
        153,
        159,
        160,
        164,
        165,
        167,
        169,
        170,
        173,
        176,
        177,
        187,
        188,
        189,
        192,
        198,
        200,
        201,
        202,
        206,
        211,
        212,
        213,
        217,
        219,
        234,
        235,
        238,
        250,
        251,
        255,
        257,
        261,
        262,
        268,
        269,
        270,
        277
      ]
    }
  },
  {
    "canonical_biomarker": "CGI-BP",
    "total_count": "131 / 283",
    "total_percentage": "46.29 %",
    "variant_percentages": {
      "CGI-S": "43.51 %",
      "CGI-BP": "25.95 %",
      "CGI-I": "16.03 %",
      "CGI-BP-S": "7.63 %",
      "CGI": "3.05 %",
      "CGI-BP-I": "2.29 %",
      "CGI-A": "1.53 %"
    },
    "rows": {
      "CGI-S": [
        10,
        12,
        24,
        26,
        27,
        33,
        35,
        37,
        40,
        43,
        47,
        51,
        57,
        68,
        73,
        76,
        78,
        79,
        98,
        102,
        116,
        123,
        125,
        130,
        131,
        132,
        143,
        152,
        161,
        168,
        169,
        173,
        176,
        206,
        218,
        227,
        228,
        246,
        247,
        261,
        262,
        268
      ],
      "CGI-BP": [
        3,
        7,
        17,
        22,
        42,
        61,
        77,
        82,
        91,
        92,
        93,
        94,
        95,
        100,
        107,
        114,
        139,
        142,
        149,
        157,
        167,
        181,
        190,
        218,
        250,
        251,
        268
      ],
      "CGI-I": [
        12,
        35,
        40,
        47,
        51,
        76,
        106,
        125,
        130,
        169,
        173,
        178,
        206,
        261,
        268
      ],
      "CGI-BP-S": [
        69,
        101,
        103,
        114,
        150,
        165,
        167,
        177,
        180
      ],
      "CGI": [
        73,
        146,
        154,
        211
      ],
      "CGI-BP-I": [
        107,
        114
      ],
      "CGI-A": [
        82,
        139
      ]
    }
  },
  {
    "canonical_biomarker": "HAM‑D",
    "total_count": "93 / 283",
    "total_percentage": "32.86 %",
    "variant_percentages": {
      "HAM‑D": "68.82 %",
      "HAM‑A": "16.13 %",
      "HRSD": "7.53 %",
      "HDRS": "4.30 %",
      "HAMA": "2.15 %"
    },
    "rows": {
      "HAM‑D": [
        6,
        9,
        12,
        22,
        26,
        35,
        37,
        41,
        44,
        46,
        47,
        61,
        62,
        76,
        78,
        80,
        88,
        89,
        96,
        102,
        108,
        155,
        156,
        164,
        169,
        176,
        177,
        180,
        187,
        191,
        194,
        196,
        201,
        207,
        211,
        213,
        261
      ],
      "HAM‑A": [
        12,
        24,
        29,
        35,
        41,
        47,
        82,
        102,
        112,
        196,
        201
      ],
      "HRSD": [
        83,
        116,
        153,
        235,
        238,
        255
      ],
      "HDRS": [
        26,
        137,
        139,
        152
      ],
      "HAMA": [
        12,
        24,
        29,
        35,
        41,
        47,
        82,
        102,
        112,
        196,
        201
      ]
    }
  },
  {
    "canonical_biomarker": "CHOL",
    "total_count": "82 / 283",
    "total_percentage": "28.98 %",
    "variant_percentages": {
      "HDL": "26.83 %",
      "TG": "19.51 %",
      "LDL": "19.51 %",
      "TC": "13.41 %",
      "VLDL‑C": "7.32 %",
      "sdLDL3": "4.88 %",
      "CHOL": "3.66 %",
      "Lp(a)": "2.44 %",
      "IDL‑C": "2.44 %"
    },
    "rows": {
      "HDL": [
        16,
        41,
        42,
        44,
        45,
        48,
        50,
        105,
        122,
        136,
        148,
        193,
        206
      ],
      "TG": [
        15,
        16,
        41,
        44,
        50,
        61,
        78,
        105,
        136,
        192,
        206,
        262
      ],
      "LDL": [
        16,
        41,
        42,
        44,
        45,
        105,
        193,
        206,
        210
      ],
      "TC": [
        16,
        41,
        70,
        71,
        78,
        105,
        122,
        148,
        193
      ],
      "VLDL‑C": [
        16
      ],
      "sdLDL3": [
        16
      ],
      "CHOL": [
        15,
        206
      ],
      "Lp(a)": [
        16
      ],
      "IDL‑C": [
        16
      ]
    }
  },
  {
    "canonical_biomarker": "MADRS",
    "total_count": "76 / 283",
    "total_percentage": "26.86 %",
    "variant_percentages": {
      "MADRS": "100.00 %"
    },
    "rows": {
      "MADRS": [
        2,
        4,
        10,
        12,
        24,
        25,
        29,
        33,
        35,
        42,
        47,
        51,
        55,
        57,
        63,
        66,
        69,
        73,
        77,
        79,
        82,
        95,
        101,
        103,
        112,
        114,
        115,
        117,
        123,
        127,
        133,
        138,
        140,
        147,
        150,
        154,
        159,
        160,
        165,
        167,
        170,
        171,
        173,
        177,
        180,
        182,
        184,
        191,
        202,
        203,
        218,
        227,
        228,
        244,
        257,
        261,
        268,
        278
      ]
    }
  },
  {
    "canonical_biomarker": "GLC",
    "total_count": "62 / 283",
    "total_percentage": "21.91 %",
    "variant_percentages": {
      "HbA1c": "16.13 %",
      "FPG": "11.29 %",
      "Hb": "11.29 %",
      "WBC": "11.29 %",
      "PLT": "9.68 %",
      "HCT": "9.68 %",
      "HOMA2-β": "8.06 %",
      "RBC": "8.06 %",
      "INS": "6.45 %",
      "GLC": "4.84 %",
      "IGR": "3.23 %"
    },
    "rows": {
      "HbA1c": [
        15,
        44,
        95,
        193,
        206,
        210,
        231,
        262
      ],
      "FPG": [
        44,
        50,
        136,
        163,
        193,
        262
      ],
      "Hb": [
        15,
        78,
        174,
        206,
        262,
        268
      ],
      "WBC": [
        15,
        78,
        206,
        262,
        268
      ],
      "PLT": [
        15,
        78,
        206,
        262,
        268
      ],
      "HCT": [
        15,
        78,
        206,
        262,
        268
      ],
      "HOMA2-β": [
        42,
        163
      ],
      "RBC": [
        15,
        78,
        206,
        262
      ],
      "INS": [
        15,
        50,
        193
      ],
      "GLC": [
        15,
        206
      ],
      "IGR": [
        47
      ]
    }
  },
  {
    "canonical_biomarker": "BMI",
    "total_count": "57 / 283",
    "total_percentage": "20.14 %",
    "variant_percentages": {
      "BMI": "24.56 %",
      "BW": "15.79 %",
      "WG": "12.28 %",
      "WC": "10.53 %",
      "ΔBW": "8.77 %",
      "BMI‑z": "7.02 %",
      "WL": "7.02 %",
      "ΔW": "5.26 %",
      "ΔBMI": "3.51 %",
      "Wt.": "3.51 %",
      "WT": "1.75 %"
    },
    "rows": {
      "BMI": [
        19,
        50,
        67,
        70,
        78,
        100,
        105,
        170,
        192,
        193,
        206,
        221,
        246
      ],
      "BW": [
        44,
        71,
        78,
        169,
        174,
        231,
        246,
        268
      ],
      "WG": [
        41,
        42,
        45,
        110,
        246
      ],
      "WC": [
        15,
        50,
        100,
        105,
        136,
        262
      ],
      "ΔBW": [
        50,
        59,
        206,
        245,
        262
      ],
      "BMI‑z": [
        43,
        206,
        221,
        262
      ],
      "WL": [
        42,
        45
      ],
      "ΔW": [
        15,
        61,
        67
      ],
      "ΔBMI": [
        59,
        61
      ],
      "Wt.": [
        105,
        193
      ],
      "WT": [
        50
      ]
    }
  },
  {
    "canonical_biomarker": "CK",
    "total_count": "48 / 283",
    "total_percentage": "16.96 %",
    "variant_percentages": {
      "ALP": "14.58 %",
      "ALT": "14.58 %",
      "AST": "14.58 %",
      "CR": "14.58 %",
      "CK": "12.50 %",
      "GGT": "8.33 %",
      "ALB": "8.33 %",
      "TBIL": "6.25 %",
      "PROT": "6.25 %"
    },
    "rows": {
      "ALP": [
        15,
        45,
        78,
        206,
        262
      ],
      "ALT": [
        45,
        65,
        78,
        206,
        262,
        268
      ],
      "AST": [
        45,
        65,
        78,
        206,
        262,
        268
      ],
      "CR": [
        15,
        78,
        206,
        226,
        262,
        268
      ],
      "CK": [
        15,
        206,
        262,
        266,
        268
      ],
      "GGT": [
        65,
        78,
        127,
        206
      ],
      "ALB": [
        15,
        206,
        262
      ],
      "TBIL": [
        78,
        206,
        262
      ],
      "PROT": [
        15,
        206
      ]
    }
  },
  {
    "canonical_biomarker": "GAF",
    "total_count": "40 / 283",
    "total_percentage": "14.13 %",
    "variant_percentages": {
      "GAF": "40.00 %",
      "CGAS": "27.50 %",
      "SOFAS": "15.00 %",
      "LIFE‑RIFT": "12.50 %",
      "GRS": "5.00 %"
    },
    "rows": {
      "GAF": [
        4,
        12,
        22,
        47,
        51,
        69,
        121,
        146,
        147,
        154,
        169,
        203
      ],
      "CGAS": [
        7,
        27,
        34,
        53,
        142,
        149,
        262,
        265
      ],
      "SOFAS": [
        22,
        146,
        160,
        257,
        275
      ],
      "LIFE‑RIFT": [
        51,
        100,
        109,
        148,
        170
      ],
      "GRS": [
        9
      ]
    }
  },
  {
    "canonical_biomarker": "AIMS",
    "total_count": "40 / 283",
    "total_percentage": "14.13 %",
    "variant_percentages": {
      "AIMS": "100.00 %"
    },
    "rows": {
      "AIMS": [
        15,
        34,
        42,
        45,
        89,
        98,
        116,
        144,
        157,
        174,
        198,
        206,
        262,
        268,
        276
      ]
    }
  },
  {
    "canonical_biomarker": "SBP",
    "total_count": "36 / 283",
    "total_percentage": "12.72 %",
    "variant_percentages": {
      "SBP": "47.22 %",
      "DBP": "38.89 %",
      "BP": "13.89 %"
    },
    "rows": {
      "SBP": [
        15,
        34,
        42,
        44,
        45,
        50,
        78,
        148,
        174,
        206,
        210,
        268
      ],
      "DBP": [
        15,
        34,
        42,
        44,
        45,
        78,
        174,
        206,
        268
      ],
      "BP": [
        50,
        136,
        158,
        199,
        231
      ]
    }
  },
  {
    "canonical_biomarker": "QLESQ",
    "total_count": "34 / 283",
    "total_percentage": "12.01 %",
    "variant_percentages": {
      "Q-LES-Q": "50.00 %",
      "SF": "35.29 %",
      "PQ-LES-Q": "5.88 %",
      "WHOQOL-BREF": "5.88 %",
      "QLESQ": "2.94 %"
    },
    "rows": {
      "Q-LES-Q": [
        12,
        35,
        47,
        62,
        102,
        109,
        137,
        150,
        159,
        173,
        220,
        258,
        259
      ],
      "SF": [
        29,
        97,
        154,
        162,
        164,
        181,
        203,
        205,
        209,
        233,
        258
      ],
      "PQ-LES-Q": [
        142,
        149
      ],
      "WHOQOL-BREF": [
        235,
        238
      ],
      "QLESQ": [
        12,
        35,
        47,
        62,
        109,
        137,
        150,
        159,
        173,
        220,
        258
      ]
    }
  }
]